scripts/__init__.py
scripts/json_generator.py
scripts/xml_runner.py
stix2elevator/__init__.py
stix2elevator/cli.py
stix2elevator/common.py
stix2elevator/confidence.py
stix2elevator/convert_cybox.py
stix2elevator/convert_pattern.py
stix2elevator/convert_stix.py
stix2elevator/convert_to_acs.py
stix2elevator/extension_definitions.py
stix2elevator/ids.py
stix2elevator/missing_policy.py
stix2elevator/options.py
stix2elevator/stix_stepper.py
stix2elevator/utils.py
stix2elevator/version.py
stix2elevator/vocab_mappings.py
stix2_elevator-4.1.7.dist-info/LICENSE
stix2_elevator-4.1.7.dist-info/METADATA
stix2_elevator-4.1.7.dist-info/WHEEL
stix2_elevator-4.1.7.dist-info/entry_points.txt
stix2_elevator-4.1.7.dist-info/top_level.txt
stix2_elevator-4.1.7.dist-info/RECORD
