Metadata-Version: 2.1
Name: stix2-elevator
Version: 4.1.7
Summary: Utility to upgrade STIX 1.X and CybOX content to STIX 2.X
Home-page: https://oasis-open.github.io/cti-documentation/
Author: OASIS Cyber Threat Intelligence Technical Committee
Author-email: cti-users@lists.oasis-open.org
Project-URL: Documentation, https://stix2-elevator.readthedocs.io/
Project-URL: Source Code, https://github.com/oasis-open/cti-stix-elevator/
Project-URL: Bug Tracker, https://github.com/oasis-open/cti-stix-elevator/issues/
Keywords: stix stix2 json xml cti cyber threat intelligence
Classifier: Programming Language :: Python :: 3
Classifier: Programming Language :: Python :: 3.7
Classifier: Programming Language :: Python :: 3.8
Classifier: Programming Language :: Python :: 3.9
Classifier: Programming Language :: Python :: 3.10
Classifier: Development Status :: 2 - Pre-Alpha
Classifier: Intended Audience :: Developers
Classifier: License :: OSI Approved :: BSD License
Classifier: Operating System :: OS Independent
Requires-Python: >=3.7
Provides-Extra: dev
Provides-Extra: test
Provides-Extra: docs
Provides-Extra: acs
License-File: LICENSE
